climatiq_mcp_server/__init__.py
climatiq_mcp_server/server.py
climatiq_mcp_server/tools.py
mseep_climatiq_mcp_server-0.2.4.dist-info/licenses/LICENSE
mseep_climatiq_mcp_server-0.2.4.dist-info/METADATA
mseep_climatiq_mcp_server-0.2.4.dist-info/WHEEL
mseep_climatiq_mcp_server-0.2.4.dist-info/entry_points.txt
mseep_climatiq_mcp_server-0.2.4.dist-info/top_level.txt
mseep_climatiq_mcp_server-0.2.4.dist-info/RECORD
