Metadata-Version: 2.4
Name: mseep-climatiq-mcp-server
Version: 0.2.4
Summary: Climatiq MCP server for carbon emission calculations
Author-email: mseep <support@skydeck.ai>
Project-URL: Homepage, https://github.com/yourusername/climatiq-mcp-server
Project-URL: Documentation, https://github.com/yourusername/climatiq-mcp-server#readme
Requires-Python: >=3.11.9
License-File: LICENSE
Requires-Dist: mcp[cli]>=1.4.1
Requires-Dist: httpx>=0.25.2
Requires-Dist: python-dotenv>=1.0.0
Requires-Dist: rich>=13.5.0
Requires-Dist: pydantic>=2.10.6
Dynamic: license-file
